app/__init__.py
app/main.py
aws_noaction-0.1.1.dist-info/METADATA
aws_noaction-0.1.1.dist-info/WHEEL
aws_noaction-0.1.1.dist-info/entry_points.txt
aws_noaction-0.1.1.dist-info/top_level.txt
aws_noaction-0.1.1.dist-info/RECORD
