Metadata-Version: 2.1
Name: aws_noaction
Version: 0.1.1
Summary: Prints current state of service from state.json on s3
Author-email: a.ryabchenko@disasm.me
Keywords: aws,s3,state management
Requires-Python: >=3.7
Requires-Dist: boto3>=1.26.0
Requires-Dist: python-dotenv>=0.19.0
